MANIFEST.in
README.txt
setup.cfg
setup.py
docs/HISTORY.txt
docs/INSTALL.txt
docs/LICENSE.txt
inqbus/__init__.py
inqbus.plone.fastmemberproperties.egg-info/PKG-INFO
inqbus.plone.fastmemberproperties.egg-info/SOURCES.txt
inqbus.plone.fastmemberproperties.egg-info/dependency_links.txt
inqbus.plone.fastmemberproperties.egg-info/entry_points.txt
inqbus.plone.fastmemberproperties.egg-info/namespace_packages.txt
inqbus.plone.fastmemberproperties.egg-info/not-zip-safe
inqbus.plone.fastmemberproperties.egg-info/requires.txt
inqbus.plone.fastmemberproperties.egg-info/top_level.txt
inqbus/plone/__init__.py
inqbus/plone/fastmemberproperties/__init__.py
inqbus/plone/fastmemberproperties/configure.zcml
inqbus/plone/fastmemberproperties/interfaces.py
inqbus/plone/fastmemberproperties/membrane.zcml
inqbus/plone/fastmemberproperties/tests.py
inqbus/plone/fastmemberproperties/tool.py
inqbus/plone/fastmemberproperties/version.txt
inqbus/plone/fastmemberproperties/profiles/default/componentregistry.xml
inqbus/plone/fastmemberproperties/profiles/default/metadata.xml
inqbus/plone/fastmemberproperties/profiles/uninstall/metadata.xml