Metadata-Version: 1.0
Name: inqbus.plone.fastmemberproperties
Version: 1.2
Summary: Provide methods to get meta data like email, fullname aso. fast as possible even for many members.
Home-page: http://inqbus-hosting.de
Author: Maik Derstappen
Author-email: maik.derstappen@inqbus.de
License: GPL
Keywords: plone,zope,member
Platform: UNKNOWN
Classifier: Framework :: Plone
Classifier: Programming Language :: Python
Classifier: Topic :: Software Development :: Libraries :: Python Modules
